Metadata-Version: 2.1
Name: pyptex
Version: 1.4.2
Summary: Python Preprocessor for (La)TeX
Home-page: https://github.com/sloisel/pyptex
Author: Sébastien Loisel
Author-email: sloisel@gmail.com
License: MIT
Project-URL: Documentation, https://htmlpreview.github.io/?https://github.com/sloisel/pyptex/blob/master/pyptex.html
Project-URL: Source, https://github.com/sloisel/pyptex
Platform: UNKNOWN
Requires-Python: >=3
License-File: LICENSE
